classoptions/__init__.py
classoptions/version.py
classoptions-0.2.0.dist-info/LICENSE.txt
classoptions-0.2.0.dist-info/METADATA
classoptions-0.2.0.dist-info/WHEEL
classoptions-0.2.0.dist-info/top_level.txt
classoptions-0.2.0.dist-info/RECORD
