Metadata-Version: 2.1
Name: classoptions
Version: 0.2.0
Summary: Implement namespaced and inheritable metadata at the class level.
Home-page: https://github.com/adrianmrit/classoptions
Author: Adrian Martinez Rodriguez
Author-email: adrianmrit@gmail.com
License: UNKNOWN
Platform: UNKNOWN
Classifier: Programming Language :: Python :: 3
Classifier: Operating System :: OS Independent
Classifier: License :: OSI Approved :: MIT License
Requires-Python: >=3.6
License-File: LICENSE.txt
